{
    "label": "murn3",
    "nodes": {
        "BulkStaticEnergy": {
            "id": "BulkStaticEnergy",
            "import_path": "pyiron_nodes.local_workflows.test.BulkStaticEnergy",
            "label": "BulkStaticEnergy",
            "parent_id": null,
            "level": 0,
            "graph": {
                "label": "BulkStaticEnergy",
                "nodes": {
                    "va_i_BulkStaticEnergy__name": {
                        "id": "va_i_BulkStaticEnergy__name",
                        "import_path": "pyiron_workflow.graph.base.identity",
                        "label": "va_i_BulkStaticEnergy__name",
                        "parent_id": "BulkStaticEnergy",
                        "level": 1,
                        "graph": null,
                        "node_type": "node",
                        "widget_type": "customNode",
                        "expanded": false
                    },
                    "va_i_BulkStaticEnergy__a": {
                        "id": "va_i_BulkStaticEnergy__a",
                        "import_path": "pyiron_workflow.graph.base.identity",
                        "label": "va_i_BulkStaticEnergy__a",
                        "parent_id": "BulkStaticEnergy",
                        "level": 1,
                        "graph": null,
                        "node_type": "node",
                        "widget_type": "customNode",
                        "expanded": false
                    },
                    "M3GNet": {
                        "id": "M3GNet",
                        "import_path": "pyiron_nodes.atomistic.engine.ase.M3GNet",
                        "label": "M3GNet",
                        "parent_id": "BulkStaticEnergy",
                        "level": 1,
                        "graph": null,
                        "node_type": "node",
                        "widget_type": "customNode",
                        "expanded": false,
                        "node": {
                            "label": "M3GNet",
                            "function": "pyiron_nodes.atomistic.engine.ase.M3GNet",
                            "inputs": {}
                        }
                    },
                    "Bulk": {
                        "id": "Bulk",
                        "import_path": "pyiron_nodes.atomistic.structure.build.Bulk",
                        "label": "Bulk",
                        "parent_id": "BulkStaticEnergy",
                        "level": 1,
                        "graph": null,
                        "node_type": "node",
                        "widget_type": "customNode",
                        "expanded": false,
                        "node": {
                            "label": "Bulk",
                            "function": "pyiron_nodes.atomistic.structure.build.Bulk",
                            "inputs": {
                                "name": "NotData"
                            }
                        }
                    },
                    "Static": {
                        "id": "Static",
                        "import_path": "pyiron_nodes.atomistic.calculator.ase.Static",
                        "label": "Static",
                        "parent_id": "BulkStaticEnergy",
                        "level": 1,
                        "graph": null,
                        "node_type": "node",
                        "widget_type": "customNode",
                        "expanded": false,
                        "node": {
                            "label": "Static",
                            "function": "pyiron_nodes.atomistic.calculator.ase.Static",
                            "inputs": {}
                        }
                    },
                    "GetEnergyLast": {
                        "id": "GetEnergyLast",
                        "import_path": "pyiron_nodes.atomistic.calculator.output.GetEnergyLast",
                        "label": "GetEnergyLast",
                        "parent_id": "BulkStaticEnergy",
                        "level": 1,
                        "graph": null,
                        "node_type": "node",
                        "widget_type": "customNode",
                        "expanded": false,
                        "node": {
                            "label": "GetEnergyLast",
                            "function": "pyiron_nodes.atomistic.calculator.output.GetEnergyLast",
                            "inputs": {}
                        }
                    },
                    "va_o_BulkStaticEnergy__BulkStaticEnergy": {
                        "id": "va_o_BulkStaticEnergy__BulkStaticEnergy",
                        "import_path": "pyiron_workflow.graph.base.identity",
                        "label": "va_o_BulkStaticEnergy__BulkStaticEnergy",
                        "parent_id": "BulkStaticEnergy",
                        "level": 1,
                        "graph": null,
                        "node_type": "node",
                        "widget_type": "customNode",
                        "expanded": false
                    },
                    "_obj_type": "pyiron_workflow.graph.base.GraphNode"
                },
                "edges": {
                    "values": [
                        {
                            "source": "va_i_BulkStaticEnergy__name",
                            "target": "Bulk",
                            "sourceHandle": "x",
                            "targetHandle": "name"
                        },
                        {
                            "source": "va_i_BulkStaticEnergy__a",
                            "target": "Bulk",
                            "sourceHandle": "x",
                            "targetHandle": "a"
                        },
                        {
                            "source": "Bulk",
                            "target": "Static",
                            "sourceHandle": "structure",
                            "targetHandle": "structure"
                        },
                        {
                            "source": "M3GNet",
                            "target": "Static",
                            "sourceHandle": "out",
                            "targetHandle": "engine"
                        },
                        {
                            "source": "Static",
                            "target": "GetEnergyLast",
                            "sourceHandle": "out",
                            "targetHandle": "calculator"
                        },
                        {
                            "source": "GetEnergyLast",
                            "target": "va_o_BulkStaticEnergy__BulkStaticEnergy",
                            "sourceHandle": "energy_last",
                            "targetHandle": "x"
                        }
                    ],
                    "obj_type": "pyiron_workflow.graph.base.GraphEdge"
                }
            },
            "node_type": "graph",
            "widget_type": "customNode",
            "expanded": false,
            "node": {
                "label": "BulkStaticEnergy",
                "function": "pyiron_nodes.local_workflows.test.BulkStaticEnergy",
                "inputs": {
                    "name": "Al",
                    "a": 3
                }
            }
        },
        "va_i_BulkStaticEnergy__name": {
            "id": "va_i_BulkStaticEnergy__name",
            "import_path": "pyiron_workflow.graph.base.identity",
            "label": "va_i_BulkStaticEnergy__name",
            "parent_id": "BulkStaticEnergy",
            "level": 1,
            "graph": null,
            "node_type": "node",
            "widget_type": "customNode",
            "expanded": false
        },
        "va_i_BulkStaticEnergy__a": {
            "id": "va_i_BulkStaticEnergy__a",
            "import_path": "pyiron_workflow.graph.base.identity",
            "label": "va_i_BulkStaticEnergy__a",
            "parent_id": "BulkStaticEnergy",
            "level": 1,
            "graph": null,
            "node_type": "node",
            "widget_type": "customNode",
            "expanded": false
        },
        "M3GNet": {
            "id": "M3GNet",
            "import_path": "pyiron_nodes.atomistic.engine.ase.M3GNet",
            "label": "M3GNet",
            "parent_id": "BulkStaticEnergy",
            "level": 1,
            "graph": null,
            "node_type": "node",
            "widget_type": "customNode",
            "expanded": false,
            "node": {
                "label": "M3GNet",
                "function": "pyiron_nodes.atomistic.engine.ase.M3GNet",
                "inputs": {}
            }
        },
        "Bulk": {
            "id": "Bulk",
            "import_path": "pyiron_nodes.atomistic.structure.build.Bulk",
            "label": "Bulk",
            "parent_id": "BulkStaticEnergy",
            "level": 1,
            "graph": null,
            "node_type": "node",
            "widget_type": "customNode",
            "expanded": false,
            "node": {
                "label": "Bulk",
                "function": "pyiron_nodes.atomistic.structure.build.Bulk",
                "inputs": {
                    "name": "NotData"
                }
            }
        },
        "Static": {
            "id": "Static",
            "import_path": "pyiron_nodes.atomistic.calculator.ase.Static",
            "label": "Static",
            "parent_id": "BulkStaticEnergy",
            "level": 1,
            "graph": null,
            "node_type": "node",
            "widget_type": "customNode",
            "expanded": false,
            "node": {
                "label": "Static",
                "function": "pyiron_nodes.atomistic.calculator.ase.Static",
                "inputs": {
                    "structure": "NotData"
                }
            }
        },
        "GetEnergyLast": {
            "id": "GetEnergyLast",
            "import_path": "pyiron_nodes.atomistic.calculator.output.GetEnergyLast",
            "label": "GetEnergyLast",
            "parent_id": "BulkStaticEnergy",
            "level": 1,
            "graph": null,
            "node_type": "node",
            "widget_type": "customNode",
            "expanded": false,
            "node": {
                "label": "GetEnergyLast",
                "function": "pyiron_nodes.atomistic.calculator.output.GetEnergyLast",
                "inputs": {}
            }
        },
        "va_o_BulkStaticEnergy__BulkStaticEnergy": {
            "id": "va_o_BulkStaticEnergy__BulkStaticEnergy",
            "import_path": "pyiron_workflow.graph.base.identity",
            "label": "va_o_BulkStaticEnergy__BulkStaticEnergy",
            "parent_id": "BulkStaticEnergy",
            "level": 1,
            "graph": null,
            "node_type": "node",
            "widget_type": "customNode",
            "expanded": false
        },
        "IterNode": {
            "id": "IterNode",
            "import_path": "pyiron_nodes.executors.IterNode",
            "label": "IterNode",
            "parent_id": null,
            "level": 0,
            "graph": null,
            "node_type": "node",
            "widget_type": "customNode",
            "expanded": false,
            "node": {
                "label": "IterNode",
                "function": "pyiron_nodes.executors.IterNode",
                "inputs": {
                    "kwarg_name": "a"
                }
            }
        },
        "Linspace": {
            "id": "Linspace",
            "import_path": "pyiron_nodes.math.Linspace",
            "label": "Linspace",
            "parent_id": null,
            "level": 0,
            "graph": null,
            "node_type": "node",
            "widget_type": "customNode",
            "expanded": false,
            "node": {
                "label": "Linspace",
                "function": "pyiron_nodes.math.Linspace",
                "inputs": {
                    "x_min": 3,
                    "x_max": 5,
                    "num_points": 7
                }
            }
        },
        "_obj_type": "pyiron_workflow.graph.base.GraphNode"
    },
    "edges": {
        "values": [
            {
                "source": "va_i_BulkStaticEnergy__name",
                "target": "Bulk",
                "sourceHandle": "x",
                "targetHandle": "name"
            },
            {
                "source": "va_i_BulkStaticEnergy__a",
                "target": "Bulk",
                "sourceHandle": "x",
                "targetHandle": "a"
            },
            {
                "source": "Bulk",
                "target": "Static",
                "sourceHandle": "structure",
                "targetHandle": "structure"
            },
            {
                "source": "M3GNet",
                "target": "Static",
                "sourceHandle": "out",
                "targetHandle": "engine"
            },
            {
                "source": "Static",
                "target": "GetEnergyLast",
                "sourceHandle": "out",
                "targetHandle": "calculator"
            },
            {
                "source": "GetEnergyLast",
                "target": "va_o_BulkStaticEnergy__BulkStaticEnergy",
                "sourceHandle": "energy_last",
                "targetHandle": "x"
            },
            {
                "source": "va_o_BulkStaticEnergy__BulkStaticEnergy",
                "target": "IterNode",
                "sourceHandle": "x",
                "targetHandle": "node"
            },
            {
                "source": "Linspace",
                "target": "IterNode",
                "sourceHandle": "linspace",
                "targetHandle": "kwarg_list"
            }
        ],
        "obj_type": "pyiron_workflow.graph.base.GraphEdge"
    }
}