{
    "label": "graph",
    "nodes": {
        "LoadGraph": {
            "id": "LoadGraph",
            "import_path": "pyiron_nodes.graphs.flow.LoadGraph",
            "label": "LoadGraph",
            "parent_id": null,
            "level": 0,
            "graph": null,
            "node_type": "node",
            "widget_type": "customNode",
            "expanded": false,
            "node": {
                "label": "LoadGraph",
                "function": "pyiron_nodes.graphs.flow.LoadGraph",
                "inputs": {
                    "path": "calphy2.json"
                }
            }
        },
        "Display": {
            "id": "Display",
            "import_path": "pyiron_nodes.graphs.flow.Display",
            "label": "Display",
            "parent_id": null,
            "level": 0,
            "graph": null,
            "node_type": "node",
            "widget_type": "customNode",
            "expanded": false,
            "node": {
                "label": "Display",
                "function": "pyiron_nodes.graphs.flow.Display",
                "inputs": {}
            }
        },
        "DisplayNodes": {
            "id": "DisplayNodes",
            "import_path": "pyiron_nodes.graphs.flow.DisplayNodes",
            "label": "DisplayNodes",
            "parent_id": null,
            "level": 0,
            "graph": null,
            "node_type": "node",
            "widget_type": "customNode",
            "expanded": false,
            "node": {
                "label": "DisplayNodes",
                "function": "pyiron_nodes.graphs.flow.DisplayNodes",
                "inputs": {}
            }
        },
        "DisplayEdges": {
            "id": "DisplayEdges",
            "import_path": "pyiron_nodes.graphs.flow.DisplayEdges",
            "label": "DisplayEdges",
            "parent_id": null,
            "level": 0,
            "graph": null,
            "node_type": "node",
            "widget_type": "customNode",
            "expanded": false,
            "node": {
                "label": "DisplayEdges",
                "function": "pyiron_nodes.graphs.flow.DisplayEdges",
                "inputs": {}
            }
        },
        "ExtractNode": {
            "id": "ExtractNode",
            "import_path": "pyiron_nodes.graphs.flow.ExtractNode",
            "label": "ExtractNode",
            "parent_id": null,
            "level": 0,
            "graph": null,
            "node_type": "node",
            "widget_type": "customNode",
            "expanded": false,
            "node": {
                "label": "ExtractNode",
                "function": "pyiron_nodes.graphs.flow.ExtractNode",
                "inputs": {
                    "node_label": "structure"
                }
            }
        },
        "NodeInput": {
            "id": "NodeInput",
            "import_path": "pyiron_nodes.graphs.flow.NodeInput",
            "label": "NodeInput",
            "parent_id": null,
            "level": 0,
            "graph": null,
            "node_type": "node",
            "widget_type": "customNode",
            "expanded": false,
            "node": {
                "label": "NodeInput",
                "function": "pyiron_nodes.graphs.flow.NodeInput",
                "inputs": {}
            }
        },
        "DisplayCode": {
            "id": "DisplayCode",
            "import_path": "pyiron_nodes.graphs.flow.DisplayCode",
            "label": "DisplayCode",
            "parent_id": null,
            "level": 0,
            "graph": null,
            "node_type": "node",
            "widget_type": "customNode",
            "expanded": false,
            "node": {
                "label": "DisplayCode",
                "function": "pyiron_nodes.graphs.flow.DisplayCode",
                "inputs": {}
            }
        },
        "GetCodeFromGraph": {
            "id": "GetCodeFromGraph",
            "import_path": "pyiron_nodes.graphs.flow.GetCodeFromGraph",
            "label": "GetCodeFromGraph",
            "parent_id": null,
            "level": 0,
            "graph": null,
            "node_type": "node",
            "widget_type": "customNode",
            "expanded": false,
            "node": {
                "label": "GetCodeFromGraph",
                "function": "pyiron_nodes.graphs.flow.GetCodeFromGraph",
                "inputs": {}
            }
        },
        "GetUpdatedGraph": {
            "id": "GetUpdatedGraph",
            "import_path": "pyiron_nodes.graphs.flow.GetUpdatedGraph",
            "label": "GetUpdatedGraph",
            "parent_id": null,
            "level": 0,
            "graph": null,
            "node_type": "node",
            "widget_type": "customNode",
            "expanded": false,
            "node": {
                "label": "GetUpdatedGraph",
                "function": "pyiron_nodes.graphs.flow.GetUpdatedGraph",
                "inputs": {}
            }
        },
        "_obj_type": "pyiron_workflow.graph.base.GraphNode"
    },
    "edges": {
        "values": [
            {
                "source": "LoadGraph",
                "target": "Display",
                "sourceHandle": "graph",
                "targetHandle": "graph"
            },
            {
                "source": "LoadGraph",
                "target": "DisplayEdges",
                "sourceHandle": "graph",
                "targetHandle": "graph"
            },
            {
                "source": "LoadGraph",
                "target": "DisplayNodes",
                "sourceHandle": "graph",
                "targetHandle": "graph"
            },
            {
                "source": "ExtractNode",
                "target": "NodeInput",
                "sourceHandle": "node",
                "targetHandle": "node"
            },
            {
                "source": "LoadGraph",
                "target": "ExtractNode",
                "sourceHandle": "graph",
                "targetHandle": "graph"
            },
            {
                "source": "GetCodeFromGraph",
                "target": "DisplayCode",
                "sourceHandle": "code",
                "targetHandle": "code"
            },
            {
                "source": "LoadGraph",
                "target": "GetUpdatedGraph",
                "sourceHandle": "graph",
                "targetHandle": "full_graph"
            },
            {
                "source": "GetUpdatedGraph",
                "target": "GetCodeFromGraph",
                "sourceHandle": "graph",
                "targetHandle": "graph"
            }
        ],
        "obj_type": "pyiron_workflow.graph.base.GraphEdge"
    }
}